<?xml version="1.0" encoding="UTF-8"?>
<beans xmlns="http://www.springframework.org/schema/beans"
	xmlns:xsi="http://www.w3.org/2001/XMLSchema-instance"
	xmlns:util="http://www.springframework.org/schema/util"
	xmlns:context="http://www.springframework.org/schema/context"
	xsi:schemaLocation="http://www.springframework.org/schema/beans https://www.springframework.org/schema/beans/spring-beans.xsd
						http://www.springframework.org/schema/util https://www.springframework.org/schema/util/spring-util.xsd
						http://www.springframework.org/schema/context http://www.springframework.org/schema/context/spring-context.xsd">
	<context:property-placeholder
		system-properties-mode="OVERRIDE" />
	<bean id="importerConfiguration"
		class="org.eclipse.tradista.core.importer.service.ImporterConfiguration">
		<property name="modules">
			<ref bean="modules" />
		</property>
		<property name="importers">
			<ref bean="importers" />
		</property>
	</bean>
	<!-- modules -->
	<util:set id="modules" set-class="java.util.TreeSet">
		<value>Fix</value>
	</util:set>
	<!-- importers -->
	<util:set id="importers">
		<!-- add references to importer beans like this : <ref bean="myImporter"/> -->
		<ref bean="fixImporter" />
	</util:set>
	<!-- importer beans declarations -->
	<bean id="fixImporter"
		class="org.eclipse.tradista.fix.importer.model.TradeCaptureReportImporter">
		<constructor-arg type="String">
			<value>MyFixTest</value>
		</constructor-arg>
		<constructor-arg type="String">
			<value>${jboss.server.config.dir}/fixImporter.properties</value>
		</constructor-arg>
		<constructor-arg>
			<idref bean="po" />
		</constructor-arg>
	</bean>
	<bean id="po" factory-bean="legalEntityBusinessDelegate"
		factory-method="getLegalEntityByShortName">
		<constructor-arg value="OAC" />
	</bean>
	<bean id="legalEntityBusinessDelegate"
		class="org.eclipse.tradista.legalentity.service.LegalEntityBusinessDelegate" />
</beans>